{
  "success": 1,
  "models": [
    {
      "id": 342,
      "name": "E-PACE",
      "mark_id": 37,
      "sort_id": 1,
      "rating": 0,
      "is_seo_active": 0,
      "rgs_code": null,
      "generations": [
        {
          "id": 555,
          "mark_name": "Jaguar",
          "model_name": "E-PACE",
          "generation_name": "2017-2021 (I)",
          "start_year": null,
          "finish_year": null,
          "image": "https://uremont-main.s3.eu-central-1.amazonaws.com/img/brands/blank_image.png",
          "images": []
        },
        {
          "id": 556,
          "mark_name": "Jaguar",
          "model_name": "E-PACE",
          "generation_name": "2020-н.в. (I, рестайлинг)",
          "start_year": null,
          "finish_year": null,
          "image": "https://uremont-main.s3.eu-central-1.amazonaws.com/img/brands/blank_image.png",
          "images": []
        }
      ]
    },
    {
      "id": 343,
      "name": "F-PACE",
      "mark_id": 37,
      "sort_id": 1,
      "rating": 0,
      "is_seo_active": 0,
      "rgs_code": null,
      "generations": [
        {
          "id": 557,
          "mark_name": "Jaguar",
          "model_name": "F-PACE",
          "generation_name": "2015-2020 (I)",
          "start_year": null,
          "finish_year": null,
          "image": "https://uremont-main.s3.eu-central-1.amazonaws.com/img/brands/blank_image.png",
          "images": []
        },
        {
          "id": 558,
          "mark_name": "Jaguar",
          "model_name": "F-PACE",
          "generation_name": "2020-н.в. (I, рестайлинг)",
          "start_year": null,
          "finish_year": null,
          "image": "https://uremont-main.s3.eu-central-1.amazonaws.com/img/brands/blank_image.png",
          "images": []
        }
      ]
    },
    {
      "id": 344,
      "name": "F-TYPE",
      "mark_id": 37,
      "sort_id": 1,
      "rating": 0,
      "is_seo_active": 0,
      "rgs_code": null,
      "generations": [
        {
          "id": 559,
          "mark_name": "Jaguar",
          "model_name": "F-TYPE",
          "generation_name": "2013-2017 (I)",
          "start_year": null,
          "finish_year": null,
          "image": "https://uremont-main.s3.eu-central-1.amazonaws.com/img/brands/blank_image.png",
          "images": []
        },
        {
          "id": 560,
          "mark_name": "Jaguar",
          "model_name": "F-TYPE",
          "generation_name": "2017-2019 (I, рестайлинг)",
          "start_year": null,
          "finish_year": null,
          "image": "https://uremont-main.s3.eu-central-1.amazonaws.com/img/brands/blank_image.png",
          "images": []
        },
        {
          "id": 561,
          "mark_name": "Jaguar",
          "model_name": "F-TYPE",
          "generation_name": "2019-н.в. (I, 2-й рестайлинг)",
          "start_year": null,
          "finish_year": null,
          "image": "https://uremont-main.s3.eu-central-1.amazonaws.com/img/brands/blank_image.png",
          "images": []
        }
      ]
    },
    {
      "id": 345,
      "name": "I-PACE",
      "mark_id": 37,
      "sort_id": 1,
      "rating": 0,
      "is_seo_active": 0,
      "rgs_code": null,
      "generations": [
        {
          "id": 562,
          "mark_name": "Jaguar",
          "model_name": "I-PACE",
          "generation_name": "2018-н.в. (I)",
          "start_year": null,
          "finish_year": null,
          "image": "https://uremont-main.s3.eu-central-1.amazonaws.com/img/brands/blank_image.png",
          "images": []
        }
      ]
    },
    {
      "id": 346,
      "name": "XE",
      "mark_id": 37,
      "sort_id": 1,
      "rating": 0,
      "is_seo_active": 0,
      "rgs_code": null,
      "generations": [
        {
          "id": 563,
          "mark_name": "Jaguar",
          "model_name": "XE",
          "generation_name": "2015-2019 (I)",
          "start_year": null,
          "finish_year": null,
          "image": "https://uremont-main.s3.eu-central-1.amazonaws.com/img/brands/blank_image.png",
          "images": []
        },
        {
          "id": 564,
          "mark_name": "Jaguar",
          "model_name": "XE",
          "generation_name": "2019-2021 (I, рестайлинг)",
          "start_year": null,
          "finish_year": null,
          "image": "https://uremont-main.s3.eu-central-1.amazonaws.com/img/brands/blank_image.png",
          "images": []
        }
      ]
    },
    {
      "id": 347,
      "name": "XF",
      "mark_id": 37,
      "sort_id": 1,
      "rating": 0,
      "is_seo_active": 0,
      "rgs_code": null,
      "generations": [
        {
          "id": 565,
          "mark_name": "Jaguar",
          "model_name": "XF",
          "generation_name": "2007-2011 (I)",
          "start_year": null,
          "finish_year": null,
          "image": "https://uremont-main.s3.eu-central-1.amazonaws.com/img/brands/blank_image.png",
          "images": []
        },
        {
          "id": 566,
          "mark_name": "Jaguar",
          "model_name": "XF",
          "generation_name": "2010-2016 (I, рестайлинг)",
          "start_year": null,
          "finish_year": null,
          "image": "https://uremont-main.s3.eu-central-1.amazonaws.com/img/brands/blank_image.png",
          "images": []
        },
        {
          "id": 567,
          "mark_name": "Jaguar",
          "model_name": "XF",
          "generation_name": "2015-2021 (II)",
          "start_year": null,
          "finish_year": null,
          "image": "https://uremont-main.s3.eu-central-1.amazonaws.com/img/brands/blank_image.png",
          "images": []
        },
        {
          "id": 568,
          "mark_name": "Jaguar",
          "model_name": "XF",
          "generation_name": "2020-н.в. (II, рестайлинг)",
          "start_year": null,
          "finish_year": null,
          "image": "https://uremont-main.s3.eu-central-1.amazonaws.com/img/brands/blank_image.png",
          "images": []
        }
      ]
    },
    {
      "id": 348,
      "name": "XJ",
      "mark_id": 37,
      "sort_id": 1,
      "rating": 0,
      "is_seo_active": 0,
      "rgs_code": null,
      "generations": [
        {
          "id": 569,
          "mark_name": "Jaguar",
          "model_name": "XJ",
          "generation_name": "2010-2016 (IX)",
          "start_year": null,
          "finish_year": null,
          "image": "https://uremont-main.s3.eu-central-1.amazonaws.com/img/brands/blank_image.png",
          "images": []
        },
        {
          "id": 570,
          "mark_name": "Jaguar",
          "model_name": "XJ",
          "generation_name": "2016-2021 (IX, рестайлинг)",
          "start_year": null,
          "finish_year": null,
          "image": "https://uremont-main.s3.eu-central-1.amazonaws.com/img/brands/blank_image.png",
          "images": []
        }
      ]
    }
  ]
}